iris/__init__.py
iris/buffer.py
iris/buffer_test.py
iris/checkpoint_evaluator.py
iris/checkpoint_util.py
iris/checkpoint_util_test.py
iris/coordinator.py
iris/coordinator_rl_test.py
iris/coordinator_test.py
iris/launch.py
iris/logger.py
iris/normalizer.py
iris/normalizer_test.py
iris/video_recorder.py
iris/algorithms/algorithm.py
iris/algorithms/ars_algorithm.py
iris/algorithms/ars_algorithm_test.py
iris/algorithms/cma_algorithm.py
iris/algorithms/cma_algorithm_test.py
iris/algorithms/es_enas_algorithm.py
iris/algorithms/es_enas_algorithm_test.py
iris/algorithms/learnable_ars_algorithm.py
iris/algorithms/multi_agent_ars_algorithm.py
iris/algorithms/multi_agent_ars_algorithm_test.py
iris/algorithms/optimizers.py
iris/algorithms/pes_algorithm.py
iris/algorithms/pes_algorithm_test.py
iris/algorithms/piars_algorithm.py
iris/algorithms/piars_algorithm_test.py
iris/algorithms/pyglove_algorithm.py
iris/algorithms/pyglove_algorithm_test.py
iris/algorithms/pyribs_algorithm.py
iris/algorithms/pyribs_algorithm_test.py
iris/algorithms/rbo_algorithm.py
iris/algorithms/rbo_algorithm_test.py
iris/algorithms/run_split_checkpoint.py
iris/algorithms/stateless_perturbation_generators.py
iris/algorithms/controllers/__init__.py
iris/algorithms/controllers/base_controller.py
iris/algorithms/controllers/controllers_test.py
iris/algorithms/controllers/hill_climb_controller.py
iris/algorithms/controllers/neat_controller.py
iris/algorithms/controllers/policy_gradient_controller.py
iris/algorithms/controllers/random_controller.py
iris/algorithms/controllers/regularized_evolution_controller.py
iris/configs/rl_example_config.py
iris/configs/simple_example_config.py
iris/maml/adaptation_optimizers.py
iris/maml/adaptation_optimizers_test.py
iris/policies/base_policy.py
iris/policies/gym_space_utils.py
iris/policies/gym_space_utils_test.py
iris/policies/hierarchical_policy.py
iris/policies/hierarchical_policy_test.py
iris/policies/implicit_policy.py
iris/policies/implicit_policy_test.py
google_iris-0.0.2a0.dist-info/LICENSE
google_iris-0.0.2a0.dist-info/METADATA
google_iris-0.0.2a0.dist-info/WHEEL
google_iris-0.0.2a0.dist-info/top_level.txt
google_iris-0.0.2a0.dist-info/RECORD
